Workbook
Name Slicer_Approval_Status: #N/A
Name Slicer_Cost_Center: #N/A
Name Slicer_Site_Name: #N/A
Name Slicer_Vendor_Name: #N/A

Sheet Invoice Master
A1: Invoice No | B1: Vendor Name | C1: Site Name | D1: Invoice Date | E1: Month | F1: PO No | G1: GRN No | H1: Amount (₹) | I1: Invoice Code | J1: Cost Center | K1: Type | L1: Funding Status | M1: Priority | N1: Approval Status | O1: Due Date | P1: Paid Date | Q1: Remarks | R1: TAT (Days) | S1: TAT Met | T1: Match Status | U1: Duplicate Flag
A2: INV-003 | B2: Gupta Electricals | C2: Noida-Plaza | D2: 45295 | E2: Jan | F2: PO-103 | G2: GRN-203 | H2: 32000 | I2: AP-ELEC | J2: CC-003 | K2: Invoice | L2: Funded | M2: Urgent | N2: Approved | O2: 45302 | P2: 45301 | Q2: - | R2: =IF(P2="-","-",P2-D2) -> 6 | S2: =IF(R2="-","-",IF(R2<=7,"Yes","No")) -> Yes | T2: =IF(AND(F2<>"MISSING",G2<>"MISSING"),"Matched","Mismatched") -> Matched | U2: =IF(COUNTIFS($B$2:B2,B2,$F$2:F2,F2,$H$2:H2,H2)>1,"DUPLICATE","OK") -> OK
A3: INV-153 | B3: Gupta Electricals | C3: Noida-Plaza | D3: 45296 | E3: Jan | F3: PO-103 | G3: GRN-203 | H3: 32000 | I3: AP-ELEC | J3: CC-003 | K3: Invoice | L3: Funded | M3: Low | N3: On Hold | O3: 45303 | P3: - | Q3: Duplicate detected | R3: =IF(P3="-","-",P3-D3) -> - | S3: =IF(R3="-","-",IF(R3<=7,"Yes","No")) -> - | T3: =IF(AND(F3<>"MISSING",G3<>"MISSING"),"Matched","Mismatched") -> Matched | U3: =IF(COUNTIFS($B$2:B3,B3,$F$2:F3,F3,$H$2:H3,H3)>1,"DUPLICATE","OK") -> DUPLICATE
A4: INV-008 | B4: Gupta Electricals | C4: Faridabad-Mall | D4: 45300 | E4: Jan | F4: PO-108 | G4: GRN-208 | H4: 67000 | I4: AP-ELEC | J4: CC-003 | K4: Invoice | L4: Funded | M4: Normal | N4: Approved | O4: 45307 | P4: 45307 | Q4: - | R4: =IF(P4="-","-",P4-D4) -> 7 | S4: =IF(R4="-","-",IF(R4<=7,"Yes","No")) -> Yes | T4: =IF(AND(F4<>"MISSING",G4<>"MISSING"),"Matched","Mismatched") -> Matched | U4: =IF(COUNTIFS($B$2:B4,B4,$F$2:F4,F4,$H$2:H4,H4)>1,"DUPLICATE","OK") -> OK
A5: INV-158 | B5: Gupta Electricals | C5: Faridabad-Mall | D5: 45301 | E5: Jan | F5: PO-108 | G5: GRN-208 | H5: 67000 | I5: AP-ELEC | J5: CC-003 | K5: Invoice | L5: Funded | M5: Normal | N5: On Hold | O5: 45308 | P5: - | Q5: Duplicate detected | R5: =IF(P5="-","-",P5-D5) -> - | S5: =IF(R5="-","-",IF(R5<=7,"Yes","No")) -> - | T5: =IF(AND(F5<>"MISSING",G5<>"MISSING"),"Matched","Mismatched") -> Matched | U5: =IF(COUNTIFS($B$2:B5,B5,$F$2:F5,F5,$H$2:H5,H5)>1,"DUPLICATE","OK") -> DUPLICATE
A6: INV-013 | B6: Gupta Electricals | C6: Delhi-HQ | D6: 45305 | E6: Jan | F6: PO-113 | G6: GRN-213 | H6: 41000 | I6: AP-ELEC | J6: CC-003 | K6: Invoice | L6: Funded | M6: Low | N6: Approved | O6: 45312 | P6: 45312 | Q6: - | R6: =IF(P6="-","-",P6-D6) -> 7 | S6: =IF(R6="-","-",IF(R6<=7,"Yes","No")) -> Yes | T6: =IF(AND(F6<>"MISSING",G6<>"MISSING"),"Matched","Mismatched") -> Matched | U6: =IF(COUNTIFS($B$2:B6,B6,$F$2:F6,F6,$H$2:H6,H6)>1,"DUPLICATE","OK") -> OK
A7: INV-018 | B7: Gupta Electricals | C7: Gurgaon-Tech | D7: 45310 | E7: Jan | F7: PO-118 | G7: GRN-218 | H7: 52000 | I7: AP-ELEC | J7: CC-003 | K7: Invoice | L7: Funded | M7: Normal | N7: Approved | O7: 45317 | P7: 45317 | Q7: - | R7: =IF(P7="-","-",P7-D7) -> 7 | S7: =IF(R7="-","-",IF(R7<=7,"Yes","No")) -> Yes | T7: =IF(AND(F7<>"MISSING",G7<>"MISSING"),"Matched","Mismatched") -> Matched | U7: =IF(COUNTIFS($B$2:B7,B7,$F$2:F7,F7,$H$2:H7,H7)>1,"DUPLICATE","OK") -> OK
A8: INV-023 | B8: Gupta Electricals | C8: Noida-Plaza | D8: 45315 | E8: Jan | F8: PO-123 | G8: GRN-223 | H8: 77000 | I8: AP-ELEC | J8: CC-003 | K8: Invoice | L8: Funded | M8: Normal | N8: Pending | O8: 45322 | P8: - | Q8: Awaiting approver | R8: =IF(P8="-","-",P8-D8) -> - | S8: =IF(R8="-","-",IF(R8<=7,"Yes","No")) -> - | T8: =IF(AND(F8<>"MISSING",G8<>"MISSING"),"Matched","Mismatched") -> Matched | U8: =IF(COUNTIFS($B$2:B8,B8,$F$2:F8,F8,$H$2:H8,H8)>1,"DUPLICATE","OK") -> OK
A9: INV-028 | B9: Gupta Electricals | C9: Faridabad-Mall | D9: 45320 | E9: Jan | F9: PO-128 | G9: GRN-228 | H9: 66000 | I9: AP-ELEC | J9: CC-003 | K9: Invoice | L9: Funded | M9: Low | N9: Approved | O9: 45327 | P9: 45327 | Q9: - | R9: =IF(P9="-","-",P9-D9) -> 7 | S9: =IF(R9="-","-",IF(R9<=7,"Yes","No")) -> Yes | T9: =IF(AND(F9<>"MISSING",G9<>"MISSING"),"Matched","Mismatched") -> Matched | U9: =IF(COUNTIFS($B$2:B9,B9,$F$2:F9,F9,$H$2:H9,H9)>1,"DUPLICATE","OK") -> OK
A10: INV-002 | B10: Mehta Contractors | C10: Gurgaon-Tech | D10: 45294 | E10: Jan | F10: PO-102 | G10: GRN-202 | H10: 78000 | I10: AP-CIVIL | J10: CC-002 | K10: Invoice | L10: Funded | M10: Normal | N10: Approved | O10: 45301 | P10: 45301 | Q10: - | R10: =IF(P10="-","-",P10-D10) -> 7 | S10: =IF(R10="-","-",IF(R10<=7,"Yes","No")) -> Yes | T10: =IF(AND(F10<>"MISSING",G10<>"MISSING"),"Matched","Mismatched") -> Matched | U10: =IF(COUNTIFS($B$2:B10,B10,$F$2:F10,F10,$H$2:H10,H10)>1,"DUPLICATE","OK") -> OK
A11: INV-152 | B11: Mehta Contractors | C11: Gurgaon-Tech | D11: 45295 | E11: Jan | F11: PO-102 | G11: GRN-202 | H11: 78000 | I11: AP-CIVIL | J11: CC-002 | K11: Invoice | L11: Funded | M11: Normal | N11: On Hold | O11: 45302 | P11: - | Q11: Duplicate of INV-002 | R11: =IF(P11="-","-",P11-D11) -> - | S11: =IF(R11="-","-",IF(R11<=7,"Yes","No")) -> - | T11: =IF(AND(F11<>"MISSING",G11<>"MISSING"),"Matched","Mismatched") -> Matched | U11: =IF(COUNTIFS($B$2:B11,B11,$F$2:F11,F11,$H$2:H11,H11)>1,"DUPLICATE","OK") -> DUPLICATE
A12: INV-007 | B12: Mehta Contractors | C12: Noida-Plaza | D12: 45299 | E12: Jan | F12: PO-107 | G12: GRN-207 | H12: 145000 | I12: AP-CIVIL | J12: CC-002 | K12: Invoice | L12: Funded | M12: Urgent | N12: Approved | O12: 45306 | P12: 45305 | Q12: - | R12: =IF(P12="-","-",P12-D12) -> 6 | S12: =IF(R12="-","-",IF(R12<=7,"Yes","No")) -> Yes | T12: =IF(AND(F12<>"MISSING",G12<>"MISSING"),"Matched","Mismatched") -> Matched | U12: =IF(COUNTIFS($B$2:B12,B12,$F$2:F12,F12,$H$2:H12,H12)>1,"DUPLICATE","OK") -> OK
A13: INV-157 | B13: Mehta Contractors | C13: Noida-Plaza | D13: 45300 | E13: Jan | F13: PO-107 | G13: GRN-207 | H13: 145000 | I13: AP-CIVIL | J13: CC-002 | K13: Invoice | L13: Funded | M13: Urgent | N13: On Hold | O13: 45307 | P13: - | Q13: Duplicate of INV-007 | R13: =IF(P13="-","-",P13-D13) -> - | S13: =IF(R13="-","-",IF(R13<=7,"Yes","No")) -> - | T13: =IF(AND(F13<>"MISSING",G13<>"MISSING"),"Matched","Mismatched") -> Matched | U13: =IF(COUNTIFS($B$2:B13,B13,$F$2:F13,F13,$H$2:H13,H13)>1,"DUPLICATE","OK") -> DUPLICATE
A14: INV-012 | B14: Mehta Contractors | C14: Faridabad-Mall | D14: 45304 | E14: Jan | F14: PO-112 | G14: GRN-212 | H14: 89000 | I14: AP-CIVIL | J14: CC-002 | K14: Invoice | L14: Funded | M14: Normal | N14: Approved | O14: 45311 | P14: 45311 | Q14: - | R14: =IF(P14="-","-",P14-D14) -> 7 | S14: =IF(R14="-","-",IF(R14<=7,"Yes","No")) -> Yes | T14: =IF(AND(F14<>"MISSING",G14<>"MISSING"),"Matched","Mismatched") -> Matched | U14: =IF(COUNTIFS($B$2:B14,B14,$F$2:F14,F14,$H$2:H14,H14)>1,"DUPLICATE","OK") -> OK
A15: INV-017 | B15: Mehta Contractors | C15: Delhi-HQ | D15: 45309 | E15: Jan | F15: PO-117 | G15: GRN-217 | H15: 165000 | I15: AP-CIVIL | J15: CC-002 | K15: Invoice | L15: Funded | M15: Normal | N15: Approved | O15: 45316 | P15: 45316 | Q15: - | R15: =IF(P15="-","-",P15-D15) -> 7 | S15: =IF(R15="-","-",IF(R15<=7,"Yes","No")) -> Yes | T15: =IF(AND(F15<>"MISSING",G15<>"MISSING"),"Matched","Mismatched") -> Matched | U15: =IF(COUNTIFS($B$2:B15,B15,$F$2:F15,F15,$H$2:H15,H15)>1,"DUPLICATE","OK") -> OK
A16: INV-022 | B16: Mehta Contractors | C16: Gurgaon-Tech | D16: 45314 | E16: Jan | F16: PO-122 | G16: GRN-222 | H16: 43000 | I16: AP-CIVIL | J16: CC-002 | K16: Invoice | L16: Pending Funds | M16: Urgent | N16: On Hold | O16: 45321 | P16: - | Q16: Funds not released | R16: =IF(P16="-","-",P16-D16) -> - | S16: =IF(R16="-","-",IF(R16<=7,"Yes","No")) -> - | T16: =IF(AND(F16<>"MISSING",G16<>"MISSING"),"Matched","Mismatched") -> Matched | U16: =IF(COUNTIFS($B$2:B16,B16,$F$2:F16,F16,$H$2:H16,H16)>1,"DUPLICATE","OK") -> OK
A17: INV-027 | B17: Mehta Contractors | C17: Noida-Plaza | D17: 45319 | E17: Jan | F17: PO-127 | G17: GRN-227 | H17: 91000 | I17: AP-CIVIL | J17: CC-002 | K17: Invoice | L17: Funded | M17: Normal | N17: Approved | O17: 45326 | P17: 45326 | Q17: - | R17: =IF(P17="-","-",P17-D17) -> 7 | S17: =IF(R17="-","-",IF(R17<=7,"Yes","No")) -> Yes | T17: =IF(AND(F17<>"MISSING",G17<>"MISSING"),"Matched","Mismatched") -> Matched | U17: =IF(COUNTIFS($B$2:B17,B17,$F$2:F17,F17,$H$2:H17,H17)>1,"DUPLICATE","OK") -> OK
A18: INV-001 | B18: Sharma Supplies | C18: Delhi-HQ | D18: 45293 | E18: Jan | F18: PO-101 | G18: GRN-201 | H18: 45000 | I18: AP-SUPPLY | J18: CC-001 | K18: Invoice | L18: Funded | M18: Normal | N18: Approved | O18: 45300 | P18: 45299 | Q18: - | R18: =IF(P18="-","-",P18-D18) -> 6 | S18: =IF(R18="-","-",IF(R18<=7,"Yes","No")) -> Yes | T18: =IF(AND(F18<>"MISSING",G18<>"MISSING"),"Matched","Mismatched") -> Matched | U18: =IF(COUNTIFS($B$2:B18,B18,$F$2:F18,F18,$H$2:H18,H18)>1,"DUPLICATE","OK") -> OK
A19: INV-151 | B19: Sharma Supplies | C19: Delhi-HQ | D19: 45294 | E19: Jan | F19: PO-101 | G19: GRN-201 | H19: 45000 | I19: AP-SUPPLY | J19: CC-001 | K19: Invoice | L19: Funded | M19: Normal | N19: On Hold | O19: 45301 | P19: - | Q19: Duplicate of INV-001 | R19: =IF(P19="-","-",P19-D19) -> - | S19: =IF(R19="-","-",IF(R19<=7,"Yes","No")) -> - | T19: =IF(AND(F19<>"MISSING",G19<>"MISSING"),"Matched","Mismatched") -> Matched | U19: =IF(COUNTIFS($B$2:B19,B19,$F$2:F19,F19,$H$2:H19,H19)>1,"DUPLICATE","OK") -> DUPLICATE
A20: INV-006 | B20: Sharma Supplies | C20: Gurgaon-Tech | D20: 45298 | E20: Jan | F20: PO-106 | G20: GRN-206 | H20: 23000 | I20: AP-SUPPLY | J20: CC-001 | K20: Invoice | L20: Funded | M20: Low | N20: Approved | O20: 45305 | P20: 45305 | Q20: - | R20: =IF(P20="-","-",P20-D20) -> 7 | S20: =IF(R20="-","-",IF(R20<=7,"Yes","No")) -> Yes | T20: =IF(AND(F20<>"MISSING",G20<>"MISSING"),"Matched","Mismatched") -> Matched | U20: =IF(COUNTIFS($B$2:B20,B20,$F$2:F20,F20,$H$2:H20,H20)>1,"DUPLICATE","OK") -> OK
A21: INV-156 | B21: Sharma Supplies | C21: Gurgaon-Tech | D21: 45299 | E21: Jan | F21: PO-106 | G21: GRN-206 | H21: 23000 | I21: AP-SUPPLY | J21: CC-001 | K21: Invoice | L21: Funded | M21: Low | N21: On Hold | O21: 45306 | P21: - | Q21: Duplicate detected | R21: =IF(P21="-","-",P21-D21) -> - | S21: =IF(R21="-","-",IF(R21<=7,"Yes","No")) -> - | T21: =IF(AND(F21<>"MISSING",G21<>"MISSING"),"Matched","Mismatched") -> Matched | U21: =IF(COUNTIFS($B$2:B21,B21,$F$2:F21,F21,$H$2:H21,H21)>1,"DUPLICATE","OK") -> DUPLICATE
A22: INV-011 | B22: Sharma Supplies | C22: Noida-Plaza | D22: 45303 | E22: Jan | F22: PO-111 | G22: GRN-211 | H22: 54000 | I22: AP-SUPPLY | J22: CC-001 | K22: Invoice | L22: Funded | M22: Normal | N22: Approved | O22: 45310 | P22: 45310 | Q22: - | R22: =IF(P22="-","-",P22-D22) -> 7 | S22: =IF(R22="-","-",IF(R22<=7,"Yes","No")) -> Yes | T22: =IF(AND(F22<>"MISSING",G22<>"MISSING"),"Matched","Mismatched") -> Matched | U22: =IF(COUNTIFS($B$2:B22,B22,$F$2:F22,F22,$H$2:H22,H22)>1,"DUPLICATE","OK") -> OK
A23: INV-016 | B23: Sharma Supplies | C23: Faridabad-Mall | D23: 45308 | E23: Jan | F23: PO-116 | G23: GRN-216 | H23: 29000 | I23: AP-SUPPLY | J23: CC-001 | K23: Invoice | L23: Funded | M23: Low | N23: Approved | O23: 45315 | P23: 45315 | Q23: - | R23: =IF(P23="-","-",P23-D23) -> 7 | S23: =IF(R23="-","-",IF(R23<=7,"Yes","No")) -> Yes | T23: =IF(AND(F23<>"MISSING",G23<>"MISSING"),"Matched","Mismatched") -> Matched | U23: =IF(COUNTIFS($B$2:B23,B23,$F$2:F23,F23,$H$2:H23,H23)>1,"DUPLICATE","OK") -> OK
A24: INV-021 | B24: Sharma Supplies | C24: Delhi-HQ | D24: 45313 | E24: Jan | F24: PO-121 | G24: GRN-221 | H24: 61000 | I24: AP-SUPPLY | J24: CC-001 | K24: Invoice | L24: Funded | M24: Normal | N24: Pending | O24: 45320 | P24: - | Q24: Awaiting approver | R24: =IF(P24="-","-",P24-D24) -> - | S24: =IF(R24="-","-",IF(R24<=7,"Yes","No")) -> - | T24: =IF(AND(F24<>"MISSING",G24<>"MISSING"),"Matched","Mismatched") -> Matched | U24: =IF(COUNTIFS($B$2:B24,B24,$F$2:F24,F24,$H$2:H24,H24)>1,"DUPLICATE","OK") -> OK
A25: INV-026 | B25: Sharma Supplies | C25: Gurgaon-Tech | D25: 45318 | E25: Jan | F25: PO-126 | G25: GRN-226 | H25: 48000 | I25: AP-SUPPLY | J25: CC-001 | K25: Invoice | L25: Funded | M25: Normal | N25: Approved | O25: 45325 | P25: 45325 | Q25: - | R25: =IF(P25="-","-",P25-D25) -> 7 | S25: =IF(R25="-","-",IF(R25<=7,"Yes","No")) -> Yes | T25: =IF(AND(F25<>"MISSING",G25<>"MISSING"),"Matched","Mismatched") -> Matched | U25: =IF(COUNTIFS($B$2:B25,B25,$F$2:F25,F25,$H$2:H25,H25)>1,"DUPLICATE","OK") -> OK
A26: INV-005 | B26: Singh & Co | C26: Delhi-HQ | D26: 45297 | E26: Jan | F26: PO-105 | G26: GRN-205 | H26: 92000 | I26: AP-UTIL | J26: CC-005 | K26: Invoice | L26: Funded | M26: Normal | N26: Approved | O26: 45304 | P26: 45304 | Q26: - | R26: =IF(P26="-","-",P26-D26) -> 7 | S26: =IF(R26="-","-",IF(R26<=7,"Yes","No")) -> Yes | T26: =IF(AND(F26<>"MISSING",G26<>"MISSING"),"Matched","Mismatched") -> Matched | U26: =IF(COUNTIFS($B$2:B26,B26,$F$2:F26,F26,$H$2:H26,H26)>1,"DUPLICATE","OK") -> OK
A27: INV-155 | B27: Singh & Co | C27: Delhi-HQ | D27: 45298 | E27: Jan | F27: PO-105 | G27: GRN-205 | H27: 92000 | I27: AP-UTIL | J27: CC-005 | K27: Invoice | L27: Funded | M27: Urgent | N27: On Hold | O27: 45305 | P27: - | Q27: Duplicate of INV-005 | R27: =IF(P27="-","-",P27-D27) -> - | S27: =IF(R27="-","-",IF(R27<=7,"Yes","No")) -> - | T27: =IF(AND(F27<>"MISSING",G27<>"MISSING"),"Matched","Mismatched") -> Matched | U27: =IF(COUNTIFS($B$2:B27,B27,$F$2:F27,F27,$H$2:H27,H27)>1,"DUPLICATE","OK") -> DUPLICATE
A28: INV-010 | B28: Singh & Co | C28: Gurgaon-Tech | D28: 45302 | E28: Jan | F28: PO-110 | G28: GRN-210 | H28: 112000 | I28: AP-UTIL | J28: CC-005 | K28: Invoice | L28: Funded | M28: Urgent | N28: Approved | O28: 45309 | P28: 45308 | Q28: - | R28: =IF(P28="-","-",P28-D28) -> 6 | S28: =IF(R28="-","-",IF(R28<=7,"Yes","No")) -> Yes | T28: =IF(AND(F28<>"MISSING",G28<>"MISSING"),"Matched","Mismatched") -> Matched | U28: =IF(COUNTIFS($B$2:B28,B28,$F$2:F28,F28,$H$2:H28,H28)>1,"DUPLICATE","OK") -> OK
A29: INV-160 | B29: Singh & Co | C29: Gurgaon-Tech | D29: 45303 | E29: Jan | F29: PO-110 | G29: GRN-210 | H29: 112000 | I29: AP-UTIL | J29: CC-005 | K29: Invoice | L29: Funded | M29: Urgent | N29: On Hold | O29: 45310 | P29: - | Q29: Duplicate of INV-010 | R29: =IF(P29="-","-",P29-D29) -> - | S29: =IF(R29="-","-",IF(R29<=7,"Yes","No")) -> - | T29: =IF(AND(F29<>"MISSING",G29<>"MISSING"),"Matched","Mismatched") -> Matched | U29: =IF(COUNTIFS($B$2:B29,B29,$F$2:F29,F29,$H$2:H29,H29)>1,"DUPLICATE","OK") -> DUPLICATE
A30: INV-015 | B30: Singh & Co | C30: Noida-Plaza | D30: 45307 | E30: Jan | F30: PO-115 | G30: GRN-215 | H30: 128000 | I30: AP-UTIL | J30: CC-005 | K30: Invoice | L30: Funded | M30: Urgent | N30: Approved | O30: 45314 | P30: 45313 | Q30: - | R30: =IF(P30="-","-",P30-D30) -> 6 | S30: =IF(R30="-","-",IF(R30<=7,"Yes","No")) -> Yes | T30: =IF(AND(F30<>"MISSING",G30<>"MISSING"),"Matched","Mismatched") -> Matched | U30: =IF(COUNTIFS($B$2:B30,B30,$F$2:F30,F30,$H$2:H30,H30)>1,"DUPLICATE","OK") -> OK
A31: INV-020 | B31: Singh & Co | C31: Faridabad-Mall | D31: 45312 | E31: Jan | F31: PO-120 | G31: GRN-220 | H31: 97000 | I31: AP-UTIL | J31: CC-005 | K31: Invoice | L31: Funded | M31: Normal | N31: Approved | O31: 45319 | P31: 45319 | Q31: - | R31: =IF(P31="-","-",P31-D31) -> 7 | S31: =IF(R31="-","-",IF(R31<=7,"Yes","No")) -> Yes | T31: =IF(AND(F31<>"MISSING",G31<>"MISSING"),"Matched","Mismatched") -> Matched | U31: =IF(COUNTIFS($B$2:B31,B31,$F$2:F31,F31,$H$2:H31,H31)>1,"DUPLICATE","OK") -> OK
A32: INV-025 | B32: Singh & Co | C32: Delhi-HQ | D32: 45317 | E32: Jan | F32: PO-125 | G32: GRN-225 | H32: 118000 | I32: AP-UTIL | J32: CC-005 | K32: Invoice | L32: Funded | M32: Urgent | N32: Pending | O32: 45324 | P32: - | Q32: Awaiting approver | R32: =IF(P32="-","-",P32-D32) -> - | S32: =IF(R32="-","-",IF(R32<=7,"Yes","No")) -> - | T32: =IF(AND(F32<>"MISSING",G32<>"MISSING"),"Matched","Mismatched") -> Matched | U32: =IF(COUNTIFS($B$2:B32,B32,$F$2:F32,F32,$H$2:H32,H32)>1,"DUPLICATE","OK") -> OK
A33: INV-030 | B33: Singh & Co | C33: Gurgaon-Tech | D33: 45322 | E33: Jan | F33: PO-130 | G33: GRN-230 | H33: 134000 | I33: AP-UTIL | J33: CC-005 | K33: Invoice | L33: Funded | M33: Urgent | N33: Approved | O33: 45329 | P33: 45328 | Q33: - | R33: =IF(P33="-","-",P33-D33) -> 6 | S33: =IF(R33="-","-",IF(R33<=7,"Yes","No")) -> Yes | T33: =IF(AND(F33<>"MISSING",G33<>"MISSING"),"Matched","Mismatched") -> Matched | U33: =IF(COUNTIFS($B$2:B33,B33,$F$2:F33,F33,$H$2:H33,H33)>1,"DUPLICATE","OK") -> OK
A34: INV-004 | B34: Verma Facilities | C34: Faridabad-Mall | D34: 45296 | E34: Jan | F34: PO-104 | G34: GRN-204 | H34: 56000 | I34: AP-MAINT | J34: CC-004 | K34: Invoice | L34: Funded | M34: Normal | N34: Approved | O34: 45303 | P34: 45303 | Q34: - | R34: =IF(P34="-","-",P34-D34) -> 7 | S34: =IF(R34="-","-",IF(R34<=7,"Yes","No")) -> Yes | T34: =IF(AND(F34<>"MISSING",G34<>"MISSING"),"Matched","Mismatched") -> Matched | U34: =IF(COUNTIFS($B$2:B34,B34,$F$2:F34,F34,$H$2:H34,H34)>1,"DUPLICATE","OK") -> OK
A35: INV-154 | B35: Verma Facilities | C35: Faridabad-Mall | D35: 45297 | E35: Jan | F35: PO-104 | G35: GRN-204 | H35: 56000 | I35: AP-MAINT | J35: CC-004 | K35: Invoice | L35: Funded | M35: Normal | N35: On Hold | O35: 45304 | P35: - | Q35: Duplicate detected | R35: =IF(P35="-","-",P35-D35) -> - | S35: =IF(R35="-","-",IF(R35<=7,"Yes","No")) -> - | T35: =IF(AND(F35<>"MISSING",G35<>"MISSING"),"Matched","Mismatched") -> Matched | U35: =IF(COUNTIFS($B$2:B35,B35,$F$2:F35,F35,$H$2:H35,H35)>1,"DUPLICATE","OK") -> DUPLICATE
A36: INV-009 | B36: Verma Facilities | C36: Delhi-HQ | D36: 45301 | E36: Jan | F36: PO-109 | G36: GRN-209 | H36: 38000 | I36: AP-MAINT | J36: CC-004 | K36: Invoice | L36: Funded | M36: Normal | N36: Approved | O36: 45308 | P36: 45308 | Q36: - | R36: =IF(P36="-","-",P36-D36) -> 7 | S36: =IF(R36="-","-",IF(R36<=7,"Yes","No")) -> Yes | T36: =IF(AND(F36<>"MISSING",G36<>"MISSING"),"Matched","Mismatched") -> Matched | U36: =IF(COUNTIFS($B$2:B36,B36,$F$2:F36,F36,$H$2:H36,H36)>1,"DUPLICATE","OK") -> OK
A37: INV-159 | B37: Verma Facilities | C37: Delhi-HQ | D37: 45302 | E37: Jan | F37: PO-109 | G37: GRN-209 | H37: 38000 | I37: AP-MAINT | J37: CC-004 | K37: Invoice | L37: Funded | M37: Normal | N37: On Hold | O37: 45309 | P37: - | Q37: Duplicate detected | R37: =IF(P37="-","-",P37-D37) -> - | S37: =IF(R37="-","-",IF(R37<=7,"Yes","No")) -> - | T37: =IF(AND(F37<>"MISSING",G37<>"MISSING"),"Matched","Mismatched") -> Matched | U37: =IF(COUNTIFS($B$2:B37,B37,$F$2:F37,F37,$H$2:H37,H37)>1,"DUPLICATE","OK") -> DUPLICATE
A38: INV-014 | B38: Verma Facilities | C38: Gurgaon-Tech | D38: 45306 | E38: Jan | F38: PO-114 | G38: GRN-214 | H38: 73000 | I38: AP-MAINT | J38: CC-004 | K38: Invoice | L38: Funded | M38: Normal | N38: Approved | O38: 45313 | P38: 45313 | Q38: - | R38: =IF(P38="-","-",P38-D38) -> 7 | S38: =IF(R38="-","-",IF(R38<=7,"Yes","No")) -> Yes | T38: =IF(AND(F38<>"MISSING",G38<>"MISSING"),"Matched","Mismatched") -> Matched | U38: =IF(COUNTIFS($B$2:B38,B38,$F$2:F38,F38,$H$2:H38,H38)>1,"DUPLICATE","OK") -> OK
A39: INV-019 | B39: Verma Facilities | C39: Noida-Plaza | D39: 45311 | E39: Jan | F39: PO-119 | G39: GRN-219 | H39: 84000 | I39: AP-MAINT | J39: CC-004 | K39: Invoice | L39: Funded | M39: Urgent | N39: Approved | O39: 45318 | P39: 45317 | Q39: - | R39: =IF(P39="-","-",P39-D39) -> 6 | S39: =IF(R39="-","-",IF(R39<=7,"Yes","No")) -> Yes | T39: =IF(AND(F39<>"MISSING",G39<>"MISSING"),"Matched","Mismatched") -> Matched | U39: =IF(COUNTIFS($B$2:B39,B39,$F$2:F39,F39,$H$2:H39,H39)>1,"DUPLICATE","OK") -> OK
A40: INV-024 | B40: Verma Facilities | C40: Faridabad-Mall | D40: 45316 | E40: Jan | F40: PO-124 | G40: GRN-224 | H40: 35000 | I40: AP-MAINT | J40: CC-004 | K40: Invoice | L40: Pending Funds | M40: Low | N40: On Hold | O40: 45323 | P40: - | Q40: Funds not released | R40: =IF(P40="-","-",P40-D40) -> - | S40: =IF(R40="-","-",IF(R40<=7,"Yes","No")) -> - | T40: =IF(AND(F40<>"MISSING",G40<>"MISSING"),"Matched","Mismatched") -> Matched | U40: =IF(COUNTIFS($B$2:B40,B40,$F$2:F40,F40,$H$2:H40,H40)>1,"DUPLICATE","OK") -> OK
A41: INV-029 | B41: Verma Facilities | C41: Delhi-HQ | D41: 45321 | E41: Jan | F41: PO-129 | G41: GRN-229 | H41: 53000 | I41: AP-MAINT | J41: CC-004 | K41: Invoice | L41: Funded | M41: Normal | N41: Approved | O41: 45328 | P41: 45328 | Q41: - | R41: =IF(P41="-","-",P41-D41) -> 7 | S41: =IF(R41="-","-",IF(R41<=7,"Yes","No")) -> Yes | T41: =IF(AND(F41<>"MISSING",G41<>"MISSING"),"Matched","Mismatched") -> Matched | U41: =IF(COUNTIFS($B$2:B41,B41,$F$2:F41,F41,$H$2:H41,H41)>1,"DUPLICATE","OK") -> OK
A42: INV-033 | B42: Gupta Electricals | C42: Delhi-HQ | D42: 45325 | E42: Feb | F42: PO-133 | G42: GRN-233 | H42: 44000 | I42: AP-ELEC | J42: CC-003 | K42: Invoice | L42: Funded | M42: Normal | N42: Approved | O42: 45332 | P42: 45332 | Q42: - | R42: =IF(P42="-","-",P42-D42) -> 7 | S42: =IF(R42="-","-",IF(R42<=7,"Yes","No")) -> Yes | T42: =IF(AND(F42<>"MISSING",G42<>"MISSING"),"Matched","Mismatched") -> Matched | U42: =IF(COUNTIFS($B$2:B42,B42,$F$2:F42,F42,$H$2:H42,H42)>1,"DUPLICATE","OK") -> OK
A43: INV-038 | B43: Gupta Electricals | C43: Gurgaon-Tech | D43: 45330 | E43: Feb | F43: PO-138 | G43: GRN-238 | H43: 58000 | I43: AP-ELEC | J43: CC-003 | K43: Invoice | L43: Funded | M43: Normal | N43: Approved | O43: 45337 | P43: 45337 | Q43: - | R43: =IF(P43="-","-",P43-D43) -> 7 | S43: =IF(R43="-","-",IF(R43<=7,"Yes","No")) -> Yes | T43: =IF(AND(F43<>"MISSING",G43<>"MISSING"),"Matched","Mismatched") -> Matched | U43: =IF(COUNTIFS($B$2:B43,B43,$F$2:F43,F43,$H$2:H43,H43)>1,"DUPLICATE","OK") -> OK
A44: INV-043 | B44: Gupta Electricals | C44: Noida-Plaza | D44: 45335 | E44: Feb | F44: PO-143 | G44: GRN-243 | H44: 82000 | I44: AP-ELEC | J44: CC-003 | K44: Invoice | L44: Funded | M44: Low | N44: Approved | O44: 45342 | P44: 45343 | Q44: Late by 1 day | R44: =IF(P44="-","-",P44-D44) -> 8 | S44: =IF(R44="-","-",IF(R44<=7,"Yes","No")) -> No | T44: =IF(AND(F44<>"MISSING",G44<>"MISSING"),"Matched","Mismatched") -> Matched | U44: =IF(COUNTIFS($B$2:B44,B44,$F$2:F44,F44,$H$2:H44,H44)>1,"DUPLICATE","OK") -> OK
A45: INV-048 | B45: Gupta Electricals | C45: Faridabad-Mall | D45: 45340 | E45: Feb | F45: PO-148 | G45: GRN-248 | H45: 63000 | I45: AP-ELEC | J45: CC-003 | K45: Invoice | L45: Funded | M45: Normal | N45: Approved | O45: 45347 | P45: 45347 | Q45: - | R45: =IF(P45="-","-",P45-D45) -> 7 | S45: =IF(R45="-","-",IF(R45<=7,"Yes","No")) -> Yes | T45: =IF(AND(F45<>"MISSING",G45<>"MISSING"),"Matched","Mismatched") -> Matched | U45: =IF(COUNTIFS($B$2:B45,B45,$F$2:F45,F45,$H$2:H45,H45)>1,"DUPLICATE","OK") -> OK
A46: INV-053 | B46: Gupta Electricals | C46: Delhi-HQ | D46: 45345 | E46: Feb | F46: PO-153 | G46: GRN-253 | H46: 71000 | I46: AP-ELEC | J46: CC-003 | K46: Invoice | L46: Funded | M46: Normal | N46: Approved | O46: 45352 | P46: 45352 | Q46: - | R46: =IF(P46="-","-",P46-D46) -> 7 | S46: =IF(R46="-","-",IF(R46<=7,"Yes","No")) -> Yes | T46: =IF(AND(F46<>"MISSING",G46<>"MISSING"),"Matched","Mismatched") -> Matched | U46: =IF(COUNTIFS($B$2:B46,B46,$F$2:F46,F46,$H$2:H46,H46)>1,"DUPLICATE","OK") -> OK
A47: INV-058 | B47: Gupta Electricals | C47: Gurgaon-Tech | D47: 45350 | E47: Feb | F47: PO-158 | G47: GRN-258 | H47: 39000 | I47: AP-ELEC | J47: CC-003 | K47: Invoice | L47: Funded | M47: Normal | N47: Approved | O47: 45357 | P47: 45359 | Q47: Late payment | R47: =IF(P47="-","-",P47-D47) -> 9 | S47: =IF(R47="-","-",IF(R47<=7,"Yes","No")) -> No | T47: =IF(AND(F47<>"MISSING",G47<>"MISSING"),"Matched","Mismatched") -> Matched | U47: =IF(COUNTIFS($B$2:B47,B47,$F$2:F47,F47,$H$2:H47,H47)>1,"DUPLICATE","OK") -> OK
A48: INV-032 | B48: Mehta Contractors | C48: Faridabad-Mall | D48: 45324 | E48: Feb | F48: PO-132 | G48: GRN-232 | H48: 108000 | I48: AP-CIVIL | J48: CC-002 | K48: Invoice | L48: Funded | M48: Normal | N48: Approved | O48: 45331 | P48: 45331 | Q48: - | R48: =IF(P48="-","-",P48-D48) -> 7 | S48: =IF(R48="-","-",IF(R48<=7,"Yes","No")) -> Yes | T48: =IF(AND(F48<>"MISSING",G48<>"MISSING"),"Matched","Mismatched") -> Matched | U48: =IF(COUNTIFS($B$2:B48,B48,$F$2:F48,F48,$H$2:H48,H48)>1,"DUPLICATE","OK") -> OK
A49: INV-037 | B49: Mehta Contractors | C49: Delhi-HQ | D49: 45329 | E49: Feb | F49: PO-137 | G49: GRN-237 | H49: 72000 | I49: AP-CIVIL | J49: CC-002 | K49: Invoice | L49: Funded | M49: Normal | N49: Pending | O49: 45336 | P49: - | Q49: Awaiting approver | R49: =IF(P49="-","-",P49-D49) -> - | S49: =IF(R49="-","-",IF(R49<=7,"Yes","No")) -> - | T49: =IF(AND(F49<>"MISSING",G49<>"MISSING"),"Matched","Mismatched") -> Matched | U49: =IF(COUNTIFS($B$2:B49,B49,$F$2:F49,F49,$H$2:H49,H49)>1,"DUPLICATE","OK") -> OK
A50: INV-042 | B50: Mehta Contractors | C50: Gurgaon-Tech | D50: 45334 | E50: Feb | F50: PO-142 | G50: GRN-242 | H50: 55000 | I50: AP-CIVIL | J50: CC-002 | K50: Invoice | L50: Funded | M50: Normal | N50: Approved | O50: 45341 | P50: 45346 | Q50: Late payment | R50: =IF(P50="-","-",P50-D50) -> 12 | S50: =IF(R50="-","-",IF(R50<=7,"Yes","No")) -> No | T50: =IF(AND(F50<>"MISSING",G50<>"MISSING"),"Matched","Mismatched") -> Matched | U50: =IF(COUNTIFS($B$2:B50,B50,$F$2:F50,F50,$H$2:H50,H50)>1,"DUPLICATE","OK") -> OK
A51: INV-047 | B51: Mehta Contractors | C51: Noida-Plaza | D51: 45339 | E51: Feb | F51: PO-147 | G51: GRN-247 | H51: 119000 | I51: AP-CIVIL | J51: CC-002 | K51: Invoice | L51: Funded | M51: Normal | N51: Approved | O51: 45346 | P51: 45346 | Q51: - | R51: =IF(P51="-","-",P51-D51) -> 7 | S51: =IF(R51="-","-",IF(R51<=7,"Yes","No")) -> Yes | T51: =IF(AND(F51<>"MISSING",G51<>"MISSING"),"Matched","Mismatched") -> Matched | U51: =IF(COUNTIFS($B$2:B51,B51,$F$2:F51,F51,$H$2:H51,H51)>1,"DUPLICATE","OK") -> OK
A52: INV-052 | B52: Mehta Contractors | C52: Faridabad-Mall | D52: 45344 | E52: Feb | F52: PO-152 | G52: GRN-252 | H52: 96000 | I52: AP-CIVIL | J52: CC-002 | K52: Invoice | L52: Funded | M52: Normal | N52: Approved | O52: 45351 | P52: 45351 | Q52: - | R52: =IF(P52="-","-",P52-D52) -> 7 | S52: =IF(R52="-","-",IF(R52<=7,"Yes","No")) -> Yes | T52: =IF(AND(F52<>"MISSING",G52<>"MISSING"),"Matched","Mismatched") -> Matched | U52: =IF(COUNTIFS($B$2:B52,B52,$F$2:F52,F52,$H$2:H52,H52)>1,"DUPLICATE","OK") -> OK
A53: INV-057 | B53: Mehta Contractors | C53: Delhi-HQ | D53: 45349 | E53: Feb | F53: PO-157 | G53: GRN-257 | H53: 83000 | I53: AP-CIVIL | J53: CC-002 | K53: Invoice | L53: Funded | M53: Normal | N53: Approved | O53: 45356 | P53: 45356 | Q53: - | R53: =IF(P53="-","-",P53-D53) -> 7 | S53: =IF(R53="-","-",IF(R53<=7,"Yes","No")) -> Yes | T53: =IF(AND(F53<>"MISSING",G53<>"MISSING"),"Matched","Mismatched") -> Matched | U53: =IF(COUNTIFS($B$2:B53,B53,$F$2:F53,F53,$H$2:H53,H53)>1,"DUPLICATE","OK") -> OK
A54: INV-031 | B54: Sharma Supplies | C54: Noida-Plaza | D54: 45323 | E54: Feb | F54: PO-131 | G54: GRN-231 | H54: 27000 | I54: AP-SUPPLY | J54: CC-001 | K54: Invoice | L54: Funded | M54: Low | N54: Approved | O54: 45330 | P54: 45330 | Q54: - | R54: =IF(P54="-","-",P54-D54) -> 7 | S54: =IF(R54="-","-",IF(R54<=7,"Yes","No")) -> Yes | T54: =IF(AND(F54<>"MISSING",G54<>"MISSING"),"Matched","Mismatched") -> Matched | U54: =IF(COUNTIFS($B$2:B54,B54,$F$2:F54,F54,$H$2:H54,H54)>1,"DUPLICATE","OK") -> OK
A55: INV-036 | B55: Sharma Supplies | C55: Faridabad-Mall | D55: 45328 | E55: Feb | F55: PO-136 | G55: GRN-236 | H55: 36000 | I55: AP-SUPPLY | J55: CC-001 | K55: Invoice | L55: Pending Funds | M55: Low | N55: On Hold | O55: 45335 | P55: - | Q55: Funds not released | R55: =IF(P55="-","-",P55-D55) -> - | S55: =IF(R55="-","-",IF(R55<=7,"Yes","No")) -> - | T55: =IF(AND(F55<>"MISSING",G55<>"MISSING"),"Matched","Mismatched") -> Matched | U55: =IF(COUNTIFS($B$2:B55,B55,$F$2:F55,F55,$H$2:H55,H55)>1,"DUPLICATE","OK") -> OK
A56: INV-041 | B56: Sharma Supplies | C56: Delhi-HQ | D56: 45333 | E56: Feb | F56: PO-141 | G56: GRN-241 | H56: 68000 | I56: AP-SUPPLY | J56: CC-001 | K56: Invoice | L56: Funded | M56: Normal | N56: Approved | O56: 45340 | P56: 45344 | Q56: Late payment | R56: =IF(P56="-","-",P56-D56) -> 11 | S56: =IF(R56="-","-",IF(R56<=7,"Yes","No")) -> No | T56: =IF(AND(F56<>"MISSING",G56<>"MISSING"),"Matched","Mismatched") -> Matched | U56: =IF(COUNTIFS($B$2:B56,B56,$F$2:F56,F56,$H$2:H56,H56)>1,"DUPLICATE","OK") -> OK
A57: INV-046 | B57: Sharma Supplies | C57: Gurgaon-Tech | D57: 45338 | E57: Feb | F57: PO-146 | G57: GRN-246 | H57: 34000 | I57: AP-SUPPLY | J57: CC-001 | K57: Invoice | L57: Funded | M57: Low | N57: Approved | O57: 45345 | P57: 45345 | Q57: - | R57: =IF(P57="-","-",P57-D57) -> 7 | S57: =IF(R57="-","-",IF(R57<=7,"Yes","No")) -> Yes | T57: =IF(AND(F57<>"MISSING",G57<>"MISSING"),"Matched","Mismatched") -> Matched | U57: =IF(COUNTIFS($B$2:B57,B57,$F$2:F57,F57,$H$2:H57,H57)>1,"DUPLICATE","OK") -> OK
A58: INV-051 | B58: Sharma Supplies | C58: Noida-Plaza | D58: 45343 | E58: Feb | F58: PO-151 | G58: GRN-251 | H58: 42000 | I58: AP-SUPPLY | J58: CC-001 | K58: Invoice | L58: Funded | M58: Low | N58: Approved | O58: 45350 | P58: 45350 | Q58: - | R58: =IF(P58="-","-",P58-D58) -> 7 | S58: =IF(R58="-","-",IF(R58<=7,"Yes","No")) -> Yes | T58: =IF(AND(F58<>"MISSING",G58<>"MISSING"),"Matched","Mismatched") -> Matched | U58: =IF(COUNTIFS($B$2:B58,B58,$F$2:F58,F58,$H$2:H58,H58)>1,"DUPLICATE","OK") -> OK
A59: INV-056 | B59: Sharma Supplies | C59: Faridabad-Mall | D59: 45348 | E59: Feb | F59: PO-156 | G59: GRN-256 | H59: 57000 | I59: AP-SUPPLY | J59: CC-001 | K59: Invoice | L59: Funded | M59: Low | N59: Approved | O59: 45355 | P59: 45355 | Q59: - | R59: =IF(P59="-","-",P59-D59) -> 7 | S59: =IF(R59="-","-",IF(R59<=7,"Yes","No")) -> Yes | T59: =IF(AND(F59<>"MISSING",G59<>"MISSING"),"Matched","Mismatched") -> Matched | U59: =IF(COUNTIFS($B$2:B59,B59,$F$2:F59,F59,$H$2:H59,H59)>1,"DUPLICATE","OK") -> OK
A60: INV-035 | B60: Singh & Co | C60: Noida-Plaza | D60: 45327 | E60: Feb | F60: PO-135 | G60: GRN-235 | H60: 156000 | I60: AP-UTIL | J60: CC-005 | K60: Invoice | L60: Funded | M60: Normal | N60: Approved | O60: 45334 | P60: 45334 | Q60: - | R60: =IF(P60="-","-",P60-D60) -> 7 | S60: =IF(R60="-","-",IF(R60<=7,"Yes","No")) -> Yes | T60: =IF(AND(F60<>"MISSING",G60<>"MISSING"),"Matched","Mismatched") -> Matched | U60: =IF(COUNTIFS($B$2:B60,B60,$F$2:F60,F60,$H$2:H60,H60)>1,"DUPLICATE","OK") -> OK
A61: INV-040 | B61: Singh & Co | C61: Faridabad-Mall | D61: 45332 | E61: Feb | F61: PO-140 | G61: GRN-240 | H61: 142000 | I61: AP-UTIL | J61: CC-005 | K61: Invoice | L61: Funded | M61: Normal | N61: Approved | O61: 45339 | P61: 45339 | Q61: - | R61: =IF(P61="-","-",P61-D61) -> 7 | S61: =IF(R61="-","-",IF(R61<=7,"Yes","No")) -> Yes | T61: =IF(AND(F61<>"MISSING",G61<>"MISSING"),"Matched","Mismatched") -> Matched | U61: =IF(COUNTIFS($B$2:B61,B61,$F$2:F61,F61,$H$2:H61,H61)>1,"DUPLICATE","OK") -> OK
A62: INV-045 | B62: Singh & Co | C62: Delhi-HQ | D62: 45337 | E62: Feb | F62: PO-145 | G62: GRN-245 | H62: 175000 | I62: AP-UTIL | J62: CC-005 | K62: Invoice | L62: Funded | M62: Urgent | N62: Approved | O62: 45344 | P62: 45344 | Q62: - | R62: =IF(P62="-","-",P62-D62) -> 7 | S62: =IF(R62="-","-",IF(R62<=7,"Yes","No")) -> Yes | T62: =IF(AND(F62<>"MISSING",G62<>"MISSING"),"Matched","Mismatched") -> Matched | U62: =IF(COUNTIFS($B$2:B62,B62,$F$2:F62,F62,$H$2:H62,H62)>1,"DUPLICATE","OK") -> OK
A63: INV-050 | B63: Singh & Co | C63: Gurgaon-Tech | D63: 45342 | E63: Feb | F63: PO-150 | G63: GRN-250 | H63: 107000 | I63: AP-UTIL | J63: CC-005 | K63: Invoice | L63: Funded | M63: Normal | N63: Approved | O63: 45349 | P63: 45349 | Q63: - | R63: =IF(P63="-","-",P63-D63) -> 7 | S63: =IF(R63="-","-",IF(R63<=7,"Yes","No")) -> Yes | T63: =IF(AND(F63<>"MISSING",G63<>"MISSING"),"Matched","Mismatched") -> Matched | U63: =IF(COUNTIFS($B$2:B63,B63,$F$2:F63,F63,$H$2:H63,H63)>1,"DUPLICATE","OK") -> OK
A64: INV-055 | B64: Singh & Co | C64: Noida-Plaza | D64: 45347 | E64: Feb | F64: PO-155 | G64: GRN-255 | H64: 188000 | I64: AP-UTIL | J64: CC-005 | K64: Invoice | L64: Funded | M64: Normal | N64: Approved | O64: 45354 | P64: 45354 | Q64: - | R64: =IF(P64="-","-",P64-D64) -> 7 | S64: =IF(R64="-","-",IF(R64<=7,"Yes","No")) -> Yes | T64: =IF(AND(F64<>"MISSING",G64<>"MISSING"),"Matched","Mismatched") -> Matched | U64: =IF(COUNTIFS($B$2:B64,B64,$F$2:F64,F64,$H$2:H64,H64)>1,"DUPLICATE","OK") -> OK
A65: INV-034 | B65: Verma Facilities | C65: Gurgaon-Tech | D65: 45326 | E65: Feb | F65: PO-134 | G65: GRN-234 | H65: 79000 | I65: AP-MAINT | J65: CC-004 | K65: Invoice | L65: Funded | M65: Urgent | N65: Approved | O65: 45333 | P65: 45332 | Q65: - | R65: =IF(P65="-","-",P65-D65) -> 6 | S65: =IF(R65="-","-",IF(R65<=7,"Yes","No")) -> Yes | T65: =IF(AND(F65<>"MISSING",G65<>"MISSING"),"Matched","Mismatched") -> Matched | U65: =IF(COUNTIFS($B$2:B65,B65,$F$2:F65,F65,$H$2:H65,H65)>1,"DUPLICATE","OK") -> OK
A66: INV-039 | B66: Verma Facilities | C66: Noida-Plaza | D66: 45331 | E66: Feb | F66: PO-139 | G66: GRN-239 | H66: 93000 | I66: AP-MAINT | J66: CC-004 | K66: Invoice | L66: Funded | M66: Urgent | N66: Approved | O66: 45338 | P66: 45337 | Q66: - | R66: =IF(P66="-","-",P66-D66) -> 6 | S66: =IF(R66="-","-",IF(R66<=7,"Yes","No")) -> Yes | T66: =IF(AND(F66<>"MISSING",G66<>"MISSING"),"Matched","Mismatched") -> Matched | U66: =IF(COUNTIFS($B$2:B66,B66,$F$2:F66,F66,$H$2:H66,H66)>1,"DUPLICATE","OK") -> OK
A67: INV-044 | B67: Verma Facilities | C67: Faridabad-Mall | D67: 45336 | E67: Feb | F67: PO-144 | G67: GRN-244 | H67: 47000 | I67: AP-MAINT | J67: CC-004 | K67: Invoice | L67: Funded | M67: Normal | N67: Approved | O67: 45343 | P67: 45345 | Q67: Late payment | R67: =IF(P67="-","-",P67-D67) -> 9 | S67: =IF(R67="-","-",IF(R67<=7,"Yes","No")) -> No | T67: =IF(AND(F67<>"MISSING",G67<>"MISSING"),"Matched","Mismatched") -> Matched | U67: =IF(COUNTIFS($B$2:B67,B67,$F$2:F67,F67,$H$2:H67,H67)>1,"DUPLICATE","OK") -> OK
... A70: INV-059 | B70: Verma Facilities | C70: Noida-Plaza | D70: 45351 | E70: Feb | F70: PO-159 | G70: GRN-259 | H70: 114000 | I70: AP-MAINT | J70: CC-004 | K70: Invoice | L70: Funded | M70: Urgent | N70: Approved | O70: 45358 | P70: 45357 | Q70: - | R70: =IF(P70="-","-",P70-D70) -> 6 | S70: =IF(R70="-","-",IF(R70<=7,"Yes","No")) -> Yes | T70: =IF(AND(F70<>"MISSING",G70<>"MISSING"),"Matched","Mismatched") -> Matched | U70: =IF(COUNTIFS($B$2:B70,B70,$F$2:F70,F70,$H$2:H70,H70)>1,"DUPLICATE","OK") -> OK
A71: INV-063 | B71: Gupta Electricals | C71: Noida-Plaza | D71: 45355 | E71: Mar | F71: MISSING | G71: GRN-263 | H71: 91000 | I71: AP-ELEC | J71: CC-003 | K71: Invoice | L71: Pending Funds | M71: Normal | N71: On Hold | O71: 45362 | P71: - | Q71: PO not found | R71: =IF(P71="-","-",P71-D71) -> - | S71: =IF(R71="-","-",IF(R71<=7,"Yes","No")) -> - | T71: =IF(AND(F71<>"MISSING",G71<>"MISSING"),"Matched","Mismatched") -> Mismatched | U71: =IF(COUNTIFS($B$2:B71,B71,$F$2:F71,F71,$H$2:H71,H71)>1,"DUPLICATE","OK") -> OK
A72: INV-068 | B72: Gupta Electricals | C72: Faridabad-Mall | D72: 45360 | E72: Mar | F72: PO-168 | G72: GRN-268 | H72: 57000 | I72: AP-ELEC | J72: CC-003 | K72: Invoice | L72: Funded | M72: Normal | N72: Approved | O72: 45367 | P72: 45367 | Q72: - | R72: =IF(P72="-","-",P72-D72) -> 7 | S72: =IF(R72="-","-",IF(R72<=7,"Yes","No")) -> Yes | T72: =IF(AND(F72<>"MISSING",G72<>"MISSING"),"Matched","Mismatched") -> Matched | U72: =IF(COUNTIFS($B$2:B72,B72,$F$2:F72,F72,$H$2:H72,H72)>1,"DUPLICATE","OK") -> OK
A73: INV-073 | B73: Gupta Electricals | C73: Delhi-HQ | D73: 45365 | E73: Mar | F73: PO-173 | G73: GRN-273 | H73: 68000 | I73: AP-ELEC | J73: CC-003 | K73: Invoice | L73: Funded | M73: Normal | N73: Approved | O73: 45372 | P73: 45372 | Q73: - | R73: =IF(P73="-","-",P73-D73) -> 7 | S73: =IF(R73="-","-",IF(R73<=7,"Yes","No")) -> Yes | T73: =IF(AND(F73<>"MISSING",G73<>"MISSING"),"Matched","Mismatched") -> Matched | U73: =IF(COUNTIFS($B$2:B73,B73,$F$2:F73,F73,$H$2:H73,H73)>1,"DUPLICATE","OK") -> OK
A74: INV-078 | B74: Gupta Electricals | C74: Gurgaon-Tech | D74: 45370 | E74: Mar | F74: PO-178 | G74: GRN-278 | H74: 76000 | I74: AP-ELEC | J74: CC-003 | K74: Invoice | L74: Funded | M74: Normal | N74: Approved | O74: 45377 | P74: 45377 | Q74: - | R74: =IF(P74="-","-",P74-D74) -> 7 | S74: =IF(R74="-","-",IF(R74<=7,"Yes","No")) -> Yes | T74: =IF(AND(F74<>"MISSING",G74<>"MISSING"),"Matched","Mismatched") -> Matched | U74: =IF(COUNTIFS($B$2:B74,B74,$F$2:F74,F74,$H$2:H74,H74)>1,"DUPLICATE","OK") -> OK
A75: INV-083 | B75: Gupta Electricals | C75: Noida-Plaza | D75: 45375 | E75: Mar | F75: PO-183 | G75: GRN-283 | H75: 43000 | I75: AP-ELEC | J75: CC-003 | K75: Invoice | L75: Funded | M75: Low | N75: Approved | O75: 45382 | P75: 45382 | Q75: - | R75: =IF(P75="-","-",P75-D75) -> 7 | S75: =IF(R75="-","-",IF(R75<=7,"Yes","No")) -> Yes | T75: =IF(AND(F75<>"MISSING",G75<>"MISSING"),"Matched","Mismatched") -> Matched | U75: =IF(COUNTIFS($B$2:B75,B75,$F$2:F75,F75,$H$2:H75,H75)>1,"DUPLICATE","OK") -> OK
A76: INV-088 | B76: Gupta Electricals | C76: Faridabad-Mall | D76: 45380 | E76: Mar | F76: PO-188 | G76: GRN-288 | H76: 54000 | I76: AP-ELEC | J76: CC-003 | K76: Invoice | L76: Funded | M76: Normal | N76: Approved | O76: 45387 | P76: 45387 | Q76: - | R76: =IF(P76="-","-",P76-D76) -> 7 | S76: =IF(R76="-","-",IF(R76<=7,"Yes","No")) -> Yes | T76: =IF(AND(F76<>"MISSING",G76<>"MISSING"),"Matched","Mismatched") -> Matched | U76: =IF(COUNTIFS($B$2:B76,B76,$F$2:F76,F76,$H$2:H76,H76)>1,"DUPLICATE","OK") -> OK
A77: INV-062 | B77: Mehta Contractors | C77: Gurgaon-Tech | D77: 45354 | E77: Mar | F77: PO-162 | G77: MISSING | H77: 48000 | I77: AP-CIVIL | J77: CC-002 | K77: Invoice | L77: Funded | M77: Normal | N77: On Hold | O77: 45361 | P77: - | Q77: GRN not received | R77: =IF(P77="-","-",P77-D77) -> - | S77: =IF(R77="-","-",IF(R77<=7,"Yes","No")) -> - | T77: =IF(AND(F77<>"MISSING",G77<>"MISSING"),"Matched","Mismatched") -> Mismatched | U77: =IF(COUNTIFS($B$2:B77,B77,$F$2:F77,F77,$H$2:H77,H77)>1,"DUPLICATE","OK") -> OK
A78: INV-067 | B78: Mehta Contractors | C78: Noida-Plaza | D78: 45359 | E78: Mar | F78: PO-167 | G78: GRN-267 | H78: 86000 | I78: AP-CIVIL | J78: CC-002 | K78: Invoice | L78: Funded | M78: Normal | N78: Approved | O78: 45366 | P78: 45366 | Q78: - | R78: =IF(P78="-","-",P78-D78) -> 7 | S78: =IF(R78="-","-",IF(R78<=7,"Yes","No")) -> Yes | T78: =IF(AND(F78<>"MISSING",G78<>"MISSING"),"Matched","Mismatched") -> Matched | U78: =IF(COUNTIFS($B$2:B78,B78,$F$2:F78,F78,$H$2:H78,H78)>1,"DUPLICATE","OK") -> OK
A79: INV-072 | B79: Mehta Contractors | C79: Faridabad-Mall | D79: 45364 | E79: Mar | F79: PO-172 | G79: GRN-272 | H79: 103000 | I79: AP-CIVIL | J79: CC-002 | K79: Invoice | L79: Funded | M79: Normal | N79: Approved | O79: 45371 | P79: 45371 | Q79: - | R79: =IF(P79="-","-",P79-D79) -> 7 | S79: =IF(R79="-","-",IF(R79<=7,"Yes","No")) -> Yes | T79: =IF(AND(F79<>"MISSING",G79<>"MISSING"),"Matched","Mismatched") -> Matched | U79: =IF(COUNTIFS($B$2:B79,B79,$F$2:F79,F79,$H$2:H79,H79)>1,"DUPLICATE","OK") -> OK
A80: INV-077 | B80: Mehta Contractors | C80: Delhi-HQ | D80: 45369 | E80: Mar | F80: PO-177 | G80: MISSING | H80: 124000 | I80: AP-CIVIL | J80: CC-002 | K80: Invoice | L80: Funded | M80: Normal | N80: On Hold | O80: 45376 | P80: - | Q80: GRN not received | R80: =IF(P80="-","-",P80-D80) -> - | S80: =IF(R80="-","-",IF(R80<=7,"Yes","No")) -> - | T80: =IF(AND(F80<>"MISSING",G80<>"MISSING"),"Matched","Mismatched") -> Mismatched | U80: =IF(COUNTIFS($B$2:B80,B80,$F$2:F80,F80,$H$2:H80,H80)>1,"DUPLICATE","OK") -> OK
A81: INV-082 | B81: Mehta Contractors | C81: Gurgaon-Tech | D81: 45374 | E81: Mar | F81: PO-182 | G81: GRN-282 | H81: 87000 | I81: AP-CIVIL | J81: CC-002 | K81: Invoice | L81: Funded | M81: Normal | N81: Approved | O81: 45381 | P81: 45381 | Q81: - | R81: =IF(P81="-","-",P81-D81) -> 7 | S81: =IF(R81="-","-",IF(R81<=7,"Yes","No")) -> Yes | T81: =IF(AND(F81<>"MISSING",G81<>"MISSING"),"Matched","Mismatched") -> Matched | U81: =IF(COUNTIFS($B$2:B81,B81,$F$2:F81,F81,$H$2:H81,H81)>1,"DUPLICATE","OK") -> OK
A82: INV-087 | B82: Mehta Contractors | C82: Noida-Plaza | D82: 45379 | E82: Mar | F82: PO-187 | G82: GRN-287 | H82: 115000 | I82: AP-CIVIL | J82: CC-002 | K82: Invoice | L82: Pending Funds | M82: Urgent | N82: On Hold | O82: 45386 | P82: - | Q82: Funds not released | R82: =IF(P82="-","-",P82-D82) -> - | S82: =IF(R82="-","-",IF(R82<=7,"Yes","No")) -> - | T82: =IF(AND(F82<>"MISSING",G82<>"MISSING"),"Matched","Mismatched") -> Matched | U82: =IF(COUNTIFS($B$2:B82,B82,$F$2:F82,F82,$H$2:H82,H82)>1,"DUPLICATE","OK") -> OK
A83: INV-076 | B83: Sharma Supplies | C83: Faridabad-Mall | D83: 45368 | E83: Mar | F83: MISSING | G83: GRN-276 | H83: 38000 | I83: AP-SUPPLY | J83: CC-001 | K83: Invoice | L83: Pending Funds | M83: Low | N83: On Hold | O83: 45375 | P83: - | Q83: PO not found | R83: =IF(P83="-","-",P83-D83) -> - | S83: =IF(R83="-","-",IF(R83<=7,"Yes","No")) -> - | T83: =IF(AND(F83<>"MISSING",G83<>"MISSING"),"Matched","Mismatched") -> Mismatched | U83: =IF(COUNTIFS($B$2:B83,B83,$F$2:F83,F83,$H$2:H83,H83)>1,"DUPLICATE","OK") -> OK
A84: INV-061 | B84: Sharma Supplies | C84: Delhi-HQ | D84: 45353 | E84: Mar | F84: MISSING | G84: GRN-261 | H84: 74000 | I84: AP-SUPPLY | J84: CC-001 | K84: Invoice | L84: Pending Funds | M84: Urgent | N84: On Hold | O84: 45360 | P84: - | Q84: PO not found | R84: =IF(P84="-","-",P84-D84) -> - | S84: =IF(R84="-","-",IF(R84<=7,"Yes","No")) -> - | T84: =IF(AND(F84<>"MISSING",G84<>"MISSING"),"Matched","Mismatched") -> Mismatched | U84: =IF(COUNTIFS($B$2:B84,B84,$F$2:F84,F84,$H$2:H84,H84)>1,"DUPLICATE","OK") -> OK
A85: INV-066 | B85: Sharma Supplies | C85: Gurgaon-Tech | D85: 45358 | E85: Mar | F85: PO-166 | G85: GRN-266 | H85: 31000 | I85: AP-SUPPLY | J85: CC-001 | K85: Invoice | L85: Funded | M85: Low | N85: Approved | O85: 45365 | P85: 45365 | Q85: - | R85: =IF(P85="-","-",P85-D85) -> 7 | S85: =IF(R85="-","-",IF(R85<=7,"Yes","No")) -> Yes | T85: =IF(AND(F85<>"MISSING",G85<>"MISSING"),"Matched","Mismatched") -> Matched | U85: =IF(COUNTIFS($B$2:B85,B85,$F$2:F85,F85,$H$2:H85,H85)>1,"DUPLICATE","OK") -> OK
A86: INV-071 | B86: Sharma Supplies | C86: Noida-Plaza | D86: 45363 | E86: Mar | F86: PO-171 | G86: GRN-271 | H86: 46000 | I86: AP-SUPPLY | J86: CC-001 | K86: Invoice | L86: Funded | M86: Low | N86: Approved | O86: 45370 | P86: 45370 | Q86: - | R86: =IF(P86="-","-",P86-D86) -> 7 | S86: =IF(R86="-","-",IF(R86<=7,"Yes","No")) -> Yes | T86: =IF(AND(F86<>"MISSING",G86<>"MISSING"),"Matched","Mismatched") -> Matched | U86: =IF(COUNTIFS($B$2:B86,B86,$F$2:F86,F86,$H$2:H86,H86)>1,"DUPLICATE","OK") -> OK
A87: INV-081 | B87: Sharma Supplies | C87: Delhi-HQ | D87: 45373 | E87: Mar | F87: PO-181 | G87: GRN-281 | H87: 51000 | I87: AP-SUPPLY | J87: CC-001 | K87: Invoice | L87: Funded | M87: Normal | N87: Approved | O87: 45380 | P87: 45380 | Q87: - | R87: =IF(P87="-","-",P87-D87) -> 7 | S87: =IF(R87="-","-",IF(R87<=7,"Yes","No")) -> Yes | T87: =IF(AND(F87<>"MISSING",G87<>"MISSING"),"Matched","Mismatched") -> Matched | U87: =IF(COUNTIFS($B$2:B87,B87,$F$2:F87,F87,$H$2:H87,H87)>1,"DUPLICATE","OK") -> OK
A88: INV-086 | B88: Sharma Supplies | C88: Gurgaon-Tech | D88: 45378 | E88: Mar | F88: PO-186 | G88: GRN-286 | H88: 28000 | I88: AP-SUPPLY | J88: CC-001 | K88: Invoice | L88: Funded | M88: Low | N88: Pending | O88: 45385 | P88: - | Q88: Awaiting approver | R88: =IF(P88="-","-",P88-D88) -> - | S88: =IF(R88="-","-",IF(R88<=7,"Yes","No")) -> - | T88: =IF(AND(F88<>"MISSING",G88<>"MISSING"),"Matched","Mismatched") -> Matched | U88: =IF(COUNTIFS($B$2:B88,B88,$F$2:F88,F88,$H$2:H88,H88)>1,"DUPLICATE","OK") -> OK
A89: INV-065 | B89: Singh & Co | C89: Delhi-HQ | D89: 45357 | E89: Mar | F89: MISSING | G89: GRN-265 | H89: 153000 | I89: AP-UTIL | J89: CC-005 | K89: Invoice | L89: Pending Funds | M89: Urgent | N89: On Hold | O89: 45364 | P89: - | Q89: PO not found | R89: =IF(P89="-","-",P89-D89) -> - | S89: =IF(R89="-","-",IF(R89<=7,"Yes","No")) -> - | T89: =IF(AND(F89<>"MISSING",G89<>"MISSING"),"Matched","Mismatched") -> Mismatched | U89: =IF(COUNTIFS($B$2:B89,B89,$F$2:F89,F89,$H$2:H89,H89)>1,"DUPLICATE","OK") -> OK
A90: INV-060 | B90: Singh & Co | C90: Faridabad-Mall | D90: 45352 | E90: Mar | F90: PO-160 | G90: GRN-260 | H90: 129000 | I90: AP-UTIL | J90: CC-005 | K90: Invoice | L90: Funded | M90: Normal | N90: Approved | O90: 45359 | P90: 45359 | Q90: - | R90: =IF(P90="-","-",P90-D90) -> 7 | S90: =IF(R90="-","-",IF(R90<=7,"Yes","No")) -> Yes | T90: =IF(AND(F90<>"MISSING",G90<>"MISSING"),"Matched","Mismatched") -> Matched | U90: =IF(COUNTIFS($B$2:B90,B90,$F$2:F90,F90,$H$2:H90,H90)>1,"DUPLICATE","OK") -> OK
A91: INV-070 | B91: Singh & Co | C91: Gurgaon-Tech | D91: 45362 | E91: Mar | F91: PO-170 | G91: GRN-270 | H91: 141000 | I91: AP-UTIL | J91: CC-005 | K91: Invoice | L91: Funded | M91: Normal | N91: Approved | O91: 45369 | P91: 45369 | Q91: - | R91: =IF(P91="-","-",P91-D91) -> 7 | S91: =IF(R91="-","-",IF(R91<=7,"Yes","No")) -> Yes | T91: =IF(AND(F91<>"MISSING",G91<>"MISSING"),"Matched","Mismatched") -> Matched | U91: =IF(COUNTIFS($B$2:B91,B91,$F$2:F91,F91,$H$2:H91,H91)>1,"DUPLICATE","OK") -> OK
A92: INV-075 | B92: Singh & Co | C92: Noida-Plaza | D92: 45367 | E92: Mar | F92: PO-175 | G92: GRN-275 | H92: 167000 | I92: AP-UTIL | J92: CC-005 | K92: Invoice | L92: Funded | M92: Normal | N92: Approved | O92: 45374 | P92: 45374 | Q92: - | R92: =IF(P92="-","-",P92-D92) -> 7 | S92: =IF(R92="-","-",IF(R92<=7,"Yes","No")) -> Yes | T92: =IF(AND(F92<>"MISSING",G92<>"MISSING"),"Matched","Mismatched") -> Matched | U92: =IF(COUNTIFS($B$2:B92,B92,$F$2:F92,F92,$H$2:H92,H92)>1,"DUPLICATE","OK") -> OK
A93: INV-080 | B93: Singh & Co | C93: Faridabad-Mall | D93: 45372 | E93: Mar | F93: PO-180 | G93: GRN-280 | H93: 138000 | I93: AP-UTIL | J93: CC-005 | K93: Invoice | L93: Funded | M93: Normal | N93: Approved | O93: 45379 | P93: 45379 | Q93: - | R93: =IF(P93="-","-",P93-D93) -> 7 | S93: =IF(R93="-","-",IF(R93<=7,"Yes","No")) -> Yes | T93: =IF(AND(F93<>"MISSING",G93<>"MISSING"),"Matched","Mismatched") -> Matched | U93: =IF(COUNTIFS($B$2:B93,B93,$F$2:F93,F93,$H$2:H93,H93)>1,"DUPLICATE","OK") -> OK
A94: INV-085 | B94: Singh & Co | C94: Delhi-HQ | D94: 45377 | E94: Mar | F94: PO-185 | G94: GRN-285 | H94: 194000 | I94: AP-UTIL | J94: CC-005 | K94: Invoice | L94: Funded | M94: Normal | N94: Approved | O94: 45384 | P94: 45384 | Q94: - | R94: =IF(P94="-","-",P94-D94) -> 7 | S94: =IF(R94="-","-",IF(R94<=7,"Yes","No")) -> Yes | T94: =IF(AND(F94<>"MISSING",G94<>"MISSING"),"Matched","Mismatched") -> Matched | U94: =IF(COUNTIFS($B$2:B94,B94,$F$2:F94,F94,$H$2:H94,H94)>1,"DUPLICATE","OK") -> OK
A95: INV-090 | B95: Singh & Co | C95: Gurgaon-Tech | D95: 45382 | E95: Mar | F95: PO-190 | G95: GRN-290 | H95: 123000 | I95: AP-UTIL | J95: CC-005 | K95: Invoice | L95: Funded | M95: Urgent | N95: Approved | O95: 45389 | P95: 45388 | Q95: - | R95: =IF(P95="-","-",P95-D95) -> 6 | S95: =IF(R95="-","-",IF(R95<=7,"Yes","No")) -> Yes | T95: =IF(AND(F95<>"MISSING",G95<>"MISSING"),"Matched","Mismatched") -> Matched | U95: =IF(COUNTIFS($B$2:B95,B95,$F$2:F95,F95,$H$2:H95,H95)>1,"DUPLICATE","OK") -> OK
A96: INV-064 | B96: Verma Facilities | C96: Faridabad-Mall | D96: 45356 | E96: Mar | F96: PO-164 | G96: MISSING | H96: 62000 | I96: AP-MAINT | J96: CC-004 | K96: Invoice | L96: Funded | M96: Low | N96: On Hold | O96: 45363 | P96: - | Q96: GRN not received | R96: =IF(P96="-","-",P96-D96) -> - | S96: =IF(R96="-","-",IF(R96<=7,"Yes","No")) -> - | T96: =IF(AND(F96<>"MISSING",G96<>"MISSING"),"Matched","Mismatched") -> Mismatched | U96: =IF(COUNTIFS($B$2:B96,B96,$F$2:F96,F96,$H$2:H96,H96)>1,"DUPLICATE","OK") -> OK
A97: INV-069 | B97: Verma Facilities | C97: Delhi-HQ | D97: 45361 | E97: Mar | F97: PO-169 | G97: GRN-269 | H97: 72000 | I97: AP-MAINT | J97: CC-004 | K97: Invoice | L97: Funded | M97: Urgent | N97: Approved | O97: 45368 | P97: 45367 | Q97: - | R97: =IF(P97="-","-",P97-D97) -> 6 | S97: =IF(R97="-","-",IF(R97<=7,"Yes","No")) -> Yes | T97: =IF(AND(F97<>"MISSING",G97<>"MISSING"),"Matched","Mismatched") -> Matched | U97: =IF(COUNTIFS($B$2:B97,B97,$F$2:F97,F97,$H$2:H97,H97)>1,"DUPLICATE","OK") -> OK
A98: INV-074 | B98: Verma Facilities | C98: Gurgaon-Tech | D98: 45366 | E98: Mar | F98: PO-174 | G98: GRN-274 | H98: 55000 | I98: AP-MAINT | J98: CC-004 | K98: Invoice | L98: Funded | M98: Urgent | N98: Approved | O98: 45373 | P98: 45372 | Q98: - | R98: =IF(P98="-","-",P98-D98) -> 6 | S98: =IF(R98="-","-",IF(R98<=7,"Yes","No")) -> Yes | T98: =IF(AND(F98<>"MISSING",G98<>"MISSING"),"Matched","Mismatched") -> Matched | U98: =IF(COUNTIFS($B$2:B98,B98,$F$2:F98,F98,$H$2:H98,H98)>1,"DUPLICATE","OK") -> OK
A99: INV-079 | B99: Verma Facilities | C99: Noida-Plaza | D99: 45371 | E99: Mar | F99: PO-179 | G99: GRN-279 | H99: 59000 | I99: AP-MAINT | J99: CC-004 | K99: Invoice | L99: Funded | M99: Urgent | N99: Approved | O99: 45378 | P99: 45377 | Q99: - | R99: =IF(P99="-","-",P99-D99) -> 6 | S99: =IF(R99="-","-",IF(R99<=7,"Yes","No")) -> Yes | T99: =IF(AND(F99<>"MISSING",G99<>"MISSING"),"Matched","Mismatched") -> Matched | U99: =IF(COUNTIFS($B$2:B99,B99,$F$2:F99,F99,$H$2:H99,H99)>1,"DUPLICATE","OK") -> OK
A100: INV-084 | B100: Verma Facilities | C100: Faridabad-Mall | D100: 45376 | E100: Mar | F100: PO-184 | G100: GRN-284 | H100: 69000 | I100: AP-MAINT | J100: CC-004 | K100: Invoice | L100: Funded | M100: Urgent | N100: Approved | O100: 45383 | P100: 45383 | Q100: - | R100: =IF(P100="-","-",P100-D100) -> 7 | S100: =IF(R100="-","-",IF(R100<=7,"Yes","No")) -> Yes | T100: =IF(AND(F100<>"MISSING",G100<>"MISSING"),"Matched","Mismatched") -> Matched | U100: =IF(COUNTIFS($B$2:B100,B100,$F$2:F100,F100,$H$2:H100,H100)>1,"DUPLICATE","OK") -> OK
A101: INV-089 | B101: Verma Facilities | C101: Delhi-HQ | D101: 45381 | E101: Mar | F101: PO-189 | G101: GRN-289 | H101: 98000 | I101: AP-MAINT | J101: CC-004 | K101: Invoice | L101: Funded | M101: Normal | N101: Approved | O101: 45388 | P101: 45388 | Q101: - | R101: =IF(P101="-","-",P101-D101) -> 7 | S101: =IF(R101="-","-",IF(R101<=7,"Yes","No")) -> Yes | T101: =IF(AND(F101<>"MISSING",G101<>"MISSING"),"Matched","Mismatched") -> Matched | U101: =IF(COUNTIFS($B$2:B101,B101,$F$2:F101,F101,$H$2:H101,H101)>1,"DUPLICATE","OK") -> OK
A102: INV-093 | B102: Gupta Electricals | C102: Delhi-HQ | D102: 45385 | E102: Apr | F102: PO-193 | G102: GRN-293 | H102: 48000 | I102: AP-ELEC | J102: CC-003 | K102: Invoice | L102: Funded | M102: Low | N102: Approved | O102: 45392 | P102: 45392 | Q102: - | R102: =IF(P102="-","-",P102-D102) -> 7 | S102: =IF(R102="-","-",IF(R102<=7,"Yes","No")) -> Yes | T102: =IF(AND(F102<>"MISSING",G102<>"MISSING"),"Matched","Mismatched") -> Matched | U102: =IF(COUNTIFS($B$2:B102,B102,$F$2:F102,F102,$H$2:H102,H102)>1,"DUPLICATE","OK") -> OK
...

Sheet Supplier
A1: Supplier Name | B1: Month | C1: Our Ledger (₹) | D1: Supplier Statement (₹) | E1: Difference (₹) | F1: Status | G1: Issue Type | H1: Follow-up Date | I1: Resolution Status | J1: Remarks
A2: Sharma Supplies | B2: Jan | C2: =SUMIFS('Invoice Master'!$H$2:$H$201,'Invoice Master'!$B$2:$B$201,Supplier!A2,'Invoice Master'!$E$2:$E$201,B2) -> 328000 | D2: =SUMIFS('Invoice Master'!$H$2:$H$201,'Invoice Master'!$B$2:$B$201,Supplier!A2,'Invoice Master'!$E$2:$E$201,Supplier!B2,'Invoice Master'!$U$2:$U$201,"OK") -> 260000 | E2: =C2-D2 -> 68000 | F2: =IF(E2=0,"Matched","Unmatched") -> Unmatched | G2: =IF(E2=0,"-","Difference due to duplicate invoice detected") -> Difference due to duplicate invoice detected | H2: 45337 | I2: Pending
A3: Mehta Contractors | B3: Jan | C3: =SUMIFS('Invoice Master'!$H$2:$H$201,'Invoice Master'!$B$2:$B$201,Supplier!A3,'Invoice Master'!$E$2:$E$201,B3) -> 834000 | D3: =SUMIFS('Invoice Master'!$H$2:$H$201,'Invoice Master'!$B$2:$B$201,Supplier!A3,'Invoice Master'!$E$2:$E$201,Supplier!B3,'Invoice Master'!$U$2:$U$201,"Ok") -> 611000 | E3: =C3-D3 -> 223000 | F3: =IF(E3=0,"Matched","Unmatched") -> Unmatched | G3: =IF(E3=0,"-","Difference due to duplicate invoice detected") -> Difference due to duplicate invoice detected | H3: 45337 | I3: Pending
A4: Gupta Electricals | B4: Jan | C4: =SUMIFS('Invoice Master'!$H$2:$H$201,'Invoice Master'!$B$2:$B$201,Supplier!A4,'Invoice Master'!$E$2:$E$201,B4) -> 434000 | D4: =SUMIFS('Invoice Master'!$H$2:$H$201,'Invoice Master'!$B$2:$B$201,Supplier!A4,'Invoice Master'!$E$2:$E$201,Supplier!B4,'Invoice Master'!$U$2:$U$201,"Ok") -> 335000 | E4: =C4-D4 -> 99000 | F4: =IF(E4=0,"Matched","Unmatched") -> Unmatched | G4: =IF(E4=0,"-","Difference due to duplicate invoice detected") -> Difference due to duplicate invoice detected | H4: 45337 | I4: Pending
A5: Verma Facilities | B5: Jan | C5: =SUMIFS('Invoice Master'!$H$2:$H$201,'Invoice Master'!$B$2:$B$201,Supplier!A5,'Invoice Master'!$E$2:$E$201,B5) -> 433000 | D5: =SUMIFS('Invoice Master'!$H$2:$H$201,'Invoice Master'!$B$2:$B$201,Supplier!A5,'Invoice Master'!$E$2:$E$201,Supplier!B5,'Invoice Master'!$U$2:$U$201,"Ok") -> 339000 | E5: =C5-D5 -> 94000 | F5: =IF(E5=0,"Matched","Unmatched") -> Unmatched | G5: =IF(E5=0,"-","Difference due to duplicate invoice detected") -> Difference due to duplicate invoice detected | H5: 45337 | I5: Pending
A6: Singh & Co | B6: Jan | C6: =SUMIFS('Invoice Master'!$H$2:$H$201,'Invoice Master'!$B$2:$B$201,Supplier!A6,'Invoice Master'!$E$2:$E$201,B6) -> 885000 | D6: =SUMIFS('Invoice Master'!$H$2:$H$201,'Invoice Master'!$B$2:$B$201,Supplier!A6,'Invoice Master'!$E$2:$E$201,Supplier!B6,'Invoice Master'!$U$2:$U$201,"Ok") -> 681000 | E6: =C6-D6 -> 204000 | F6: =IF(E6=0,"Matched","Unmatched") -> Unmatched | G6: =IF(E6=0,"-","Difference due to duplicate invoice detected") -> Difference due to duplicate invoice detected | H6: 45337 | I6: Pending
A7: Sharma Supplies | B7: Feb | C7: =SUMIFS('Invoice Master'!$H$2:$H$201,'Invoice Master'!$B$2:$B$201,Supplier!A7,'Invoice Master'!$E$2:$E$201,B7) -> 264000 | D7: =SUMIFS('Invoice Master'!$H$2:$H$201,'Invoice Master'!$B$2:$B$201,Supplier!A7,'Invoice Master'!$E$2:$E$201,Supplier!B7,'Invoice Master'!$U$2:$U$201,"Ok") -> 264000 | E7: =C7-D7 -> 0 | F7: =IF(E7=0,"Matched","Unmatched") -> Matched | G7: =IF(E7=0,"-","Difference due to duplicate invoice detected") -> - | H7: - | I7: -
A8: Mehta Contractors | B8: Feb | C8: =SUMIFS('Invoice Master'!$H$2:$H$201,'Invoice Master'!$B$2:$B$201,Supplier!A8,'Invoice Master'!$E$2:$E$201,B8) -> 533000 | D8: =SUMIFS('Invoice Master'!$H$2:$H$201,'Invoice Master'!$B$2:$B$201,Supplier!A8,'Invoice Master'!$E$2:$E$201,Supplier!B8,'Invoice Master'!$U$2:$U$201,"Ok") -> 533000 | E8: =C8-D8 -> 0 | F8: =IF(E8=0,"Matched","Unmatched") -> Matched | G8: =IF(E8=0,"-","Difference due to duplicate invoice detected") -> - | H8: - | I8: -
A9: Gupta Electricals | B9: Feb | C9: =SUMIFS('Invoice Master'!$H$2:$H$201,'Invoice Master'!$B$2:$B$201,Supplier!A9,'Invoice Master'!$E$2:$E$201,B9) -> 357000 | D9: =SUMIFS('Invoice Master'!$H$2:$H$201,'Invoice Master'!$B$2:$B$201,Supplier!A9,'Invoice Master'!$E$2:$E$201,Supplier!B9,'Invoice Master'!$U$2:$U$201,"Ok") -> 357000 | E9: =C9-D9 -> 0 | F9: =IF(E9=0,"Matched","Unmatched") -> Matched | G9: =IF(E9=0,"-","Difference due to duplicate invoice detected") -> - | H9: - | I9: -
A10: Verma Facilities | B10: Feb | C10: =SUMIFS('Invoice Master'!$H$2:$H$201,'Invoice Master'!$B$2:$B$201,Supplier!A10,'Invoice Master'!$E$2:$E$201,B10) -> 470000 | D10: =SUMIFS('Invoice Master'!$H$2:$H$201,'Invoice Master'!$B$2:$B$201,Supplier!A10,'Invoice Master'!$E$2:$E$201,Supplier!B10,'Invoice Master'!$U$2:$U$201,"Ok") -> 470000 | E10: =C10-D10 -> 0 | F10: =IF(E10=0,"Matched","Unmatched") -> Matched | G10: =IF(E10=0,"-","Difference due to duplicate invoice detected") -> - | H10: - | I10: -
A11: Singh & Co | B11: Feb | C11: =SUMIFS('Invoice Master'!$H$2:$H$201,'Invoice Master'!$B$2:$B$201,Supplier!A11,'Invoice Master'!$E$2:$E$201,B11) -> 768000 | D11: =SUMIFS('Invoice Master'!$H$2:$H$201,'Invoice Master'!$B$2:$B$201,Supplier!A11,'Invoice Master'!$E$2:$E$201,Supplier!B11,'Invoice Master'!$U$2:$U$201,"Ok") -> 768000 | E11: =C11-D11 -> 0 | F11: =IF(E11=0,"Matched","Unmatched") -> Matched | G11: =IF(E11=0,"-","Difference due to duplicate invoice detected") -> - | H11: - | I11: -
A12: Sharma Supplies | B12: Mar | C12: =SUMIFS('Invoice Master'!$H$2:$H$201,'Invoice Master'!$B$2:$B$201,Supplier!A12,'Invoice Master'!$E$2:$E$201,B12) -> 268000 | D12: =SUMIFS('Invoice Master'!$H$2:$H$201,'Invoice Master'!$B$2:$B$201,Supplier!A12,'Invoice Master'!$E$2:$E$201,Supplier!B12,'Invoice Master'!$U$2:$U$201,"Ok") -> 268000 | E12: =C12-D12 -> 0 | F12: =IF(E12=0,"Matched","Unmatched") -> Matched | G12: =IF(E12=0,"-","Difference due to duplicate invoice detected") -> - | H12: - | I12: -
A13: Mehta Contractors | B13: Mar | C13: =SUMIFS('Invoice Master'!$H$2:$H$201,'Invoice Master'!$B$2:$B$201,Supplier!A13,'Invoice Master'!$E$2:$E$201,B13) -> 563000 | D13: =SUMIFS('Invoice Master'!$H$2:$H$201,'Invoice Master'!$B$2:$B$201,Supplier!A13,'Invoice Master'!$E$2:$E$201,Supplier!B13,'Invoice Master'!$U$2:$U$201,"Ok") -> 563000 | E13: =C13-D13 -> 0 | F13: =IF(E13=0,"Matched","Unmatched") -> Matched | G13: =IF(E13=0,"-","Difference due to duplicate invoice detected") -> - | H13: - | I13: -
A14: Gupta Electricals | B14: Mar | C14: =SUMIFS('Invoice Master'!$H$2:$H$201,'Invoice Master'!$B$2:$B$201,Supplier!A14,'Invoice Master'!$E$2:$E$201,B14) -> 389000 | D14: =SUMIFS('Invoice Master'!$H$2:$H$201,'Invoice Master'!$B$2:$B$201,Supplier!A14,'Invoice Master'!$E$2:$E$201,Supplier!B14,'Invoice Master'!$U$2:$U$201,"Ok") -> 389000 | E14: =C14-D14 -> 0 | F14: =IF(E14=0,"Matched","Unmatched") -> Matched | G14: =IF(E14=0,"-","Difference due to duplicate invoice detected") -> - | H14: - | I14: -
A15: Verma Facilities | B15: Mar | C15: =SUMIFS('Invoice Master'!$H$2:$H$201,'Invoice Master'!$B$2:$B$201,Supplier!A15,'Invoice Master'!$E$2:$E$201,B15) -> 415000 | D15: =SUMIFS('Invoice Master'!$H$2:$H$201,'Invoice Master'!$B$2:$B$201,Supplier!A15,'Invoice Master'!$E$2:$E$201,Supplier!B15,'Invoice Master'!$U$2:$U$201,"Ok") -> 415000 | E15: =C15-D15 -> 0 | F15: =IF(E15=0,"Matched","Unmatched") -> Matched | G15: =IF(E15=0,"-","Difference due to duplicate invoice detected") -> - | H15: - | I15: -
A16: Singh & Co | B16: Mar | C16: =SUMIFS('Invoice Master'!$H$2:$H$201,'Invoice Master'!$B$2:$B$201,Supplier!A16,'Invoice Master'!$E$2:$E$201,B16) -> 1045000 | D16: =SUMIFS('Invoice Master'!$H$2:$H$201,'Invoice Master'!$B$2:$B$201,Supplier!A16,'Invoice Master'!$E$2:$E$201,Supplier!B16,'Invoice Master'!$U$2:$U$201,"Ok") -> 1045000 | E16: =C16-D16 -> 0 | F16: =IF(E16=0,"Matched","Unmatched") -> Matched | G16: =IF(E16=0,"-","Difference due to duplicate invoice detected") -> - | H16: - | I16: -
A17: Sharma Supplies | B17: Apr | C17: =SUMIFS('Invoice Master'!$H$2:$H$201,'Invoice Master'!$B$2:$B$201,Supplier!A17,'Invoice Master'!$E$2:$E$201,B17) -> 287000 | D17: =SUMIFS('Invoice Master'!$H$2:$H$201,'Invoice Master'!$B$2:$B$201,Supplier!A17,'Invoice Master'!$E$2:$E$201,Supplier!B17,'Invoice Master'!$U$2:$U$201,"Ok") -> 287000 | E17: =C17-D17 -> 0 | F17: =IF(E17=0,"Matched","Unmatched") -> Matched | G17: =IF(E17=0,"-","Difference due to duplicate invoice detected") -> - | H17: - | I17: -
A18: Mehta Contractors | B18: Apr | C18: =SUMIFS('Invoice Master'!$H$2:$H$201,'Invoice Master'!$B$2:$B$201,Supplier!A18,'Invoice Master'!$E$2:$E$201,B18) -> 510000 | D18: =SUMIFS('Invoice Master'!$H$2:$H$201,'Invoice Master'!$B$2:$B$201,Supplier!A18,'Invoice Master'!$E$2:$E$201,Supplier!B18,'Invoice Master'!$U$2:$U$201,"Ok") -> 510000 | E18: =C18-D18 -> 0 | F18: =IF(E18=0,"Matched","Unmatched") -> Matched | G18: =IF(E18=0,"-","Difference due to duplicate invoice detected") -> - | H18: - | I18: -
... A36: Singh & Co | B36: Jul | C36: =SUMIFS('Invoice Master'!$H$2:$H$201,'Invoice Master'!$B$2:$B$201,Supplier!A36,'Invoice Master'!$E$2:$E$201,B36) -> 324000 | D36: =SUMIFS('Invoice Master'!$H$2:$H$201,'Invoice Master'!$B$2:$B$201,Supplier!A36,'Invoice Master'!$E$2:$E$201,Supplier!B36,'Invoice Master'!$U$2:$U$201,"Ok") -> 324000 | E36: =C36-D36 -> 0 | F36: =IF(E36=0,"Matched","Unmatched") -> Matched | G36: =IF(E36=0,"-","Difference due to duplicate invoice detected") -> - | H36: - | I36: -

Sheet MIS Report
A1: Metric | B1: Value | C1: Target | D1: Status
A2: Total Invoices | B2: =COUNTA('Invoice Master'!A2:A201) -> 200 | C2: - | D2: =IF(B2>=200,"✓ On Track","✗ Monitor") -> ✓ On Track
A3: Approved % | B3: =COUNTIF('Invoice Master'!$N$2:$N$201,"Approved")/B2 -> 0.825 | C3: 1 | D3: =IF(B3>=100,"✓ On Track","✗ Action Needed") -> ✗ Action Needed
A4: Pending | B4: =COUNTIF('Invoice Master'!$N$2:$N$201,A4) -> 9 | C4: 0 | D4: =IF(B4=0,"✓ Clear","✗ Action Needed") -> ✗ Action Needed
A5: On Hold | B5: =COUNTIF('Invoice Master'!$N$2:$N$201,A5) -> 26 | C5: 0 | D5: =IF(B5=0,"✓ Clear","✗ Action Needed") -> ✗ Action Needed
A6: Overdues | B6: =COUNTIFS('Invoice Master'!R2:R201,"-",'Invoice Master'!U2:U201,"ok") -> 25 | C6: 0 | D6: =IF(B6=0,"✓ Clear","✗ Action Needed") -> ✗ Action Needed
A7: Mismatches | B7: =COUNTIF('Invoice Master'!$T$2:$T$201,"Mismatched") -> 9 | C7: 0 | D7: =IF(B7=0,"✓ Clear","✗ Investigate") -> ✗ Investigate
A8: Duplicates Detected | B8: =COUNTIF('Invoice Master'!$U$2:$U$201,"DUPLICATE") -> 10 | C8: 0 | D8: =IF(B8=0,"✓ Clear","✗ Block Payment") -> ✗ Block Payment
A9: TAT Met | B9: =COUNTIF('Invoice Master'!$S$2:$S$201,"Yes")/B2 -> 0.785 | C9: 0.95 | D9: =IF(B9=B2,"✓ 100% TAT","✗ Escalate") -> ✗ Escalate
A10: TAT Breached | B10: =COUNTIF('Invoice Master'!$S$2:$S$201,"No") -> 8 | C10: 0 | D10: =IF(B10=0,"✓ Clear","✗ Escalate") -> ✗ Escalate
A11: Avg TAT | B11: =ROUND(AVERAGE('Invoice Master'!R2:R201),1)&" Days" -> 6.9 Days | C11: 7 | D11: =IF(AVERAGE('Invoice Master'!R2:R201)<7,"✓ On Track","✗ Action Needed") -> ✓ On Track
A12: Total Invoice Value (₹) | B12: =SUMIF('Invoice Master'!$N$2:$N$201,"Approved",'Invoice Master'!$H$2:$H$201) -> 13349000 | C12: - | D12: =IF(B12>0,"✓ Tracked","-") -> ✓ Tracked
A13: Credit Notes Processed | B13: =COUNTIF('Invoice Master'!K:K,"Credit Note") -> 9 | C13: - | D13: =IF(B13>0,"✓ Tracked","-") -> ✓ Tracked

Sheet Pivot
A2: Site and Vendor | D2: Month | H2: Status
A4: Duplicate Flag | B4: OK | D4: Month | E4: Amount | F4: Total Invoices | H4: Approval Status | I4: Total Invoices
D5: Jan | E5: 2914000 | F5: 40 | H5: Pending | I5: 9
A6: Site Name | B6: Avg Amount | D6: Feb | E6: 2392000 | F6: 29 | H6: On Hold | I6: 26
A7: Gurgaon-Tech | B7: 70020.833 | D7: Mar | E7: 2680000 | F7: 31 | H7: Approved | I7: 165
A8: Faridabad-Mall | B8: 73723.404 | D8: Apr | E8: 2562000 | F8: 30
A9: Delhi-HQ | B9: 85145.833 | D9: May | E9: 1918000 | F9: 30
A10: Noida-Plaza | B10: 89106.383 | D10: Jun | E10: 2495000 | F10: 30
D11: Jul | E11: 828000 | F11: 10
A13: Duplicate Flag | B13: OK | D13: Duplicate Flag | E13: OK
D14: Paid Date | E14: -
A15: Vendor Name | B15: Amount
A16: Singh & Co | B16: 5395000 | D16: Month | E16: Total Invoices
A17: Mehta Contractors | B17: 3271000 | D17: Jan | E17: 5
A18: Verma Facilities | B18: 2812000 | D18: Feb | E18: 2
A19: Gupta Electricals | B19: 2134000 | D19: Mar | E19: 9
A20: Sharma Supplies | B20: 1489000 | D20: Apr | E20: 2
D21: May | E21: 2
D22: Jun | E22: 3
D23: Jul | E23: 2

Sheet KPI Dashboard
B1: AP KPI DASHBOARD — RICS & ISAE COMPLIANCE
B4: Process Control Point | C4: Standard | D4: Compliance Status | E4: Evidence
B5: All invoices matched to approved PO before processing | C5: RICS | D5: ✓ Compliant | E5: 3-Way Match column in Invoice Master
B6: GRN confirmed before payment release | C6: ISAE 3402 | D6: ✓ Compliant | E6: GRN No. verified in Invoice Master
B7: Duplicate invoice detection process in place | C7: RICS | D7: ✓ Compliant | E7: Duplicate Detector sheet active
B8: Payment approved by designated approver | C8: RICS | D8: ✓ Compliant | E8: Approval Status tracked in Invoice Master
B9: Supplier reconciliation performed monthly | C9: ISAE 3402 | D9: ✓ Compliant | E9: Supplier Recon sheet — monthly cadence
B10: Funding confirmed before payment run | C10: RICS | D10: ✓ Compliant | E10: Funding Status column tracked
B11: TAT monitored and reported to Team Leader | C11: ISAE 3402 | D11: ✓ Compliant | E11: TAT Met column + MIS Report
B12: Exceptions escalated and logged | C12: RICS | D12: ✓ Compliant | E12: Remarks column + On Hold status
B13: KPIs reported weekly | C13: ISAE 3402 | D13: ✓ Compliant | E13: KPI Dashboard updated weekly
B14: Client financial data maintained confidentially | C14: RICS | D14: ✓ Compliant | E14: Access restricted to authorised users
B15: Production log maintained per invoice | C15: ISAE 3402 | D15: ✓ Compliant | E15: Invoice Master serves as production log
B16: Credit notes processed and reconciled | C16: RICS | D16: ✓ Compliant | E16: Credit Note type tracked in Invoice Master
B18: AP KPI DASHBOARD
